py3_tools/__init__.py
py3_tools/socat_unix.py
py3_tools/gitee/__init__.py
py3_tools/gitee/gitee_pr_stat.py
py3_tools/py_debug/__init__.py
py3_tools/py_debug/debug_on_except.py
py3_tools/py_debug/debug_utils.py
py3_tools/py_debug/example_remote_pdb.py
py3_tools/py_debug/example_web_pdb.py
py3_tools/py_debug/ex_tmp/__init__.py
py3_tools/py_debug/ex_tmp/ipdb_socket.py
py3_tools/py_debug/ex_tmp/iterminal_socket.py
py3_tools/py_debug/ex_tmp/pdb_fileout.py
py3_tools/py_debug/ex_tmp/pdb_socket.py
py3_tools/py_debug/ex_tmp/pdb_stdout.py
py3_tools/py_debug/ex_tmp/socat_tools/gpt.py
py3_tools/py_debug/ex_tmp/socat_tools/loop copy.py
py3_tools/py_debug/ex_tmp/socat_tools/loop2.py
py3_tools/py_debug/ex_tmp/socat_tools/new_pty.py
py3_tools/py_debug/ex_tmp/socat_tools/pty_examples.py
py3_tools/py_debug/ex_tmp/socat_tools/run-socket.py
py3_tools/py_debug/ex_tmp/socat_tools/run.py
py3_tools/py_debug/ex_tmp/socat_tools/test_terminal_vias_socket.py
py3_tools/py_debug/socket/pty_class.py
py3_tools/py_debug/socket/socket_class.py
py3_tools_hqx-1.3.0.dist-info/licenses/LICENSE
py3_tools_hqx-1.3.0.dist-info/METADATA
py3_tools_hqx-1.3.0.dist-info/WHEEL
py3_tools_hqx-1.3.0.dist-info/top_level.txt
py3_tools_hqx-1.3.0.dist-info/RECORD
