Metadata-Version: 2.4
Name: py3_tools_hqx
Version: 1.3.0
Summary: Personal tools collection for various utilities
Author-email: hhqx <your.email@example.com>
Maintainer-email: hhqx <your.email@example.com>
License: MIT
Project-URL: Homepage, https://github.com/hhqx/py3_tools
Project-URL: Bug Tracker, https://github.com/hhqx/py3_tools/issues
Project-URL: Documentation, https://github.com/hhqx/py3_tools/tree/master/README.md
Classifier: Programming Language :: Python :: 3
Classifier: License :: OSI Approved :: MIT License
Classifier: Operating System :: OS Independent
Requires-Python: >=3.7
License-File: LICENSE
Requires-Dist: ipdb>=0.13.0
Requires-Dist: web-pdb>=1.5.0
Requires-Dist: click
Provides-Extra: dev
Requires-Dist: pytest>=7.0.0; extra == "dev"
Requires-Dist: pytest-cov; extra == "dev"
Requires-Dist: pytest-mock; extra == "dev"
Requires-Dist: black>=23.0.0; extra == "dev"
Requires-Dist: flake8>=6.0.0; extra == "dev"
Requires-Dist: isort>=5.0.0; extra == "dev"
Requires-Dist: mypy>=1.0.0; extra == "dev"
Requires-Dist: build>=0.10.0; extra == "dev"
Requires-Dist: twine>=4.0.0; extra == "dev"
Requires-Dist: sphinx; extra == "dev"
Requires-Dist: sphinx-rtd-theme; extra == "dev"
Provides-Extra: py-debug
Requires-Dist: ipdb>=0.13.0; extra == "py-debug"
Requires-Dist: web-pdb>=1.5.0; extra == "py-debug"
Requires-Dist: torch>=1.12.0; extra == "py-debug"
Requires-Dist: numpy>=1.20.0; extra == "py-debug"
Provides-Extra: gitee
Requires-Dist: requests>=2.28.0; extra == "gitee"
Requires-Dist: pandas>=1.5.0; extra == "gitee"
Requires-Dist: beautifulsoup4>=4.11.0; extra == "gitee"
Requires-Dist: pyyaml>=6.0; extra == "gitee"
Provides-Extra: full
Requires-Dist: py3_tools_hqx[dev,gitee,py_debug]; extra == "full"
Dynamic: license-file
